fzk3014/__init__.py
fzk3014/circuit_analyzer.py
fzk3014/graph.py
fzk3014/oracles.py
fzk3014/quantum.py
fzk3014/utils.py
fzk3014-0.0.0.dist-info/METADATA
fzk3014-0.0.0.dist-info/WHEEL
fzk3014-0.0.0.dist-info/top_level.txt
fzk3014-0.0.0.dist-info/RECORD
