Metadata-Version: 2.4
Name: fzk3014
Version: 0.0.0
Requires-Dist: numpy<=2.0
Requires-Dist: scipy>=1.13.1
Requires-Dist: networkx>=3.4
Requires-Dist: matplotlib>=3.10
Dynamic: requires-dist
